thunderclouds/__init__.py
thunderclouds/main.py
thunderclouds/thundercloud.py
thundercloud-1.0.1.dist-info/LICENSE
thundercloud-1.0.1.dist-info/METADATA
thundercloud-1.0.1.dist-info/WHEEL
thundercloud-1.0.1.dist-info/entry_points.txt
thundercloud-1.0.1.dist-info/top_level.txt
thundercloud-1.0.1.dist-info/RECORD
